har_to_case/__init__.py
har_to_case/main.py
har_to_case/parse_har.py
har_to_case/common/__init__.py
har_to_case/common/tools.py
har2jicase-0.1.10.dist-info/METADATA
har2jicase-0.1.10.dist-info/WHEEL
har2jicase-0.1.10.dist-info/entry_points.txt
har2jicase-0.1.10.dist-info/top_level.txt
har2jicase-0.1.10.dist-info/zip-safe
har2jicase-0.1.10.dist-info/RECORD
