Metadata-Version: 2.1
Name: har2jicase
Version: 0.1.10
Summary: 将浏览器录制的har文件转换为极星测试框架的YAML测试用例
Home-page: 
Author: Captain Ji
Author-email: qing.ji@extremevision.com.cn
License: MIT
Keywords: har json compare comparison case yaml yml
Requires-Python: >=3.6.13
Requires-Dist: loguru (~=0.6.0)
Requires-Dist: haralyzer (~=2.2.0)
Requires-Dist: PyYAML (~=6.0)
